building_energy_storage_simulation/__init__.py
building_energy_storage_simulation/battery.py
building_energy_storage_simulation/building_simulation.py
building_energy_storage_simulation/environment.py
building_energy_storage_simulation/utils.py
building_energy_storage_simulation/data/preprocessed/building_load_profile.csv
building_energy_storage_simulation/data/preprocessed/electricity_load_profile.csv
building_energy_storage_simulation/data/preprocessed/electricity_price_profile.csv
building_energy_storage_simulation/data/preprocessed/solar_generation_profile.csv
building_energy_storage_simulation-0.9.0.dist-info/LICENCE
building_energy_storage_simulation-0.9.0.dist-info/METADATA
building_energy_storage_simulation-0.9.0.dist-info/WHEEL
building_energy_storage_simulation-0.9.0.dist-info/top_level.txt
building_energy_storage_simulation-0.9.0.dist-info/RECORD
