Metadata-Version: 2.1
Name: building-energy-storage-simulation
Version: 0.9.0
Summary: A simulation of a building to optimize energy storage utilization.
Home-page: https://github.com/tobirohrer/building-energy-storage-simulation
Author: Tobias Rohrer
Author-email: tobias.rohrer@outlook.com
License-File: LICENCE
Requires-Dist: gymnasium
Requires-Dist: pandas
Requires-Dist: numpy
Provides-Extra: docs
Requires-Dist: sphinx ; extra == 'docs'
Provides-Extra: tests
Requires-Dist: pytest ; extra == 'tests'
